LICENSE
MANIFEST.in
README.rst
setup.cfg
setup.py
versioneer.py
artellapipe/__init__.py
artellapipe/libs/__init__.py
artellapipe/libs/pyblish/__init__.py
artellapipe/libs/pyblish/__logging__.ini
artellapipe/libs/pyblish/__version__.py
artellapipe/libs/pyblish/_version.py
artellapipe/libs/pyblish/collectors/__init__.py
artellapipe/libs/pyblish/collectors/general/__init__.py
artellapipe/libs/pyblish/collectors/general/collectcomment.py
artellapipe/libs/pyblish/collectors/layout/__init__.py
artellapipe/libs/pyblish/collectors/layout/collectshots.py
artellapipe/libs/pyblish/collectors/modeling/__init__.py
artellapipe/libs/pyblish/collectors/modeling/collectgeometry.py
artellapipe/libs/pyblish/core/__init__.py
artellapipe/libs/pyblish/core/publisher.py
artellapipe/libs/pyblish/core/tool.py
artellapipe/libs/pyblish/extractors/__init__.py
artellapipe/libs/pyblish/extractors/layout/__init__.py
artellapipe/libs/pyblish/extractors/layout/shot.py
artellapipe/libs/pyblish/managers/__init__.py
artellapipe/libs/pyblish/managers/pyblishplugins.py
artellapipe/libs/pyblish/validators/__init__.py
artellapipe/libs/pyblish/validators/modeling/__init__.py
artellapipe/libs/pyblish/validators/modeling/general/__init__.py
artellapipe/libs/pyblish/validators/modeling/general/cleanhistory.py
artellapipe/libs/pyblish/validators/modeling/general/displaylayers.py
artellapipe/libs/pyblish/validators/modeling/general/emptygroups.py
artellapipe/libs/pyblish/validators/modeling/general/smoothpreview.py
artellapipe/libs/pyblish/validators/modeling/general/visibility.py
artellapipe/libs/pyblish/validators/modeling/shaders/__init__.py
artellapipe/libs/pyblish/validators/modeling/shaders/shaders.py
artellapipe/libs/pyblish/validators/modeling/topology/__init__.py
artellapipe/libs/pyblish/validators/modeling/topology/hardedges.py
artellapipe/libs/pyblish/validators/modeling/topology/lamina.py
artellapipe/libs/pyblish/validators/modeling/topology/ngons.py
artellapipe_libs_pyblish.egg-info/PKG-INFO
artellapipe_libs_pyblish.egg-info/SOURCES.txt
artellapipe_libs_pyblish.egg-info/dependency_links.txt
artellapipe_libs_pyblish.egg-info/not-zip-safe
artellapipe_libs_pyblish.egg-info/requires.txt
artellapipe_libs_pyblish.egg-info/top_level.txt
