Metadata-Version: 2.1
Name: artellapipe-libs-pyblish
Version: 0.0.6
Summary: Pyblish plugins for ArtellaPipe
Home-page: https://github.com/ArtellaPipe/artellapipe-libs-pyblish
Author: Tomas Poveda
Author-email: tpovedatd@gmail.com
License: MIT
Platform: UNKNOWN
Provides-Extra: dev
Provides-Extra: test
